{
    "projectName": "graphqlnoteapp",
    "projectPath": "/nfs/2016/d/dstolz/amplify-practice/graphql-note-app",
    "defaultEditor": "code",
    "frontendHandler": {
        "javascript": "/nfs/2016/d/dstolz/.brew/lib/node_modules/@aws-amplify/cli/node_modules/amplify-frontend-javascript"
    },
    "javascript": {
        "framework": "react",
        "config": {
            "SourceDir": "src",
            "DistributionDir": "build",
            "BuildCommand": "npm run-script build",
            "StartCommand": "npm run-script start"
        }
    },
    "providers": {
        "awscloudformation": "/nfs/2016/d/dstolz/.brew/lib/node_modules/@aws-amplify/cli/node_modules/amplify-provider-awscloudformation"
    }
}